{
  "_class": "group",
  "booleanOperation": 0,
  "clippingMaskMode": 0,
  "do_objectID": "7B7EE099-00D7-4749-8661-5E1AB28EB8A5",
  "exportOptions": {
    "_class": "exportOptions",
    "do_objectID": "576B83A2-D8BC-4DD3-8ADA-8F33B87E4B38",
    "exportFormats": [
    ],
    "includedLayerIds": [
    ],
    "layerOptions": 0,
    "shouldTrim": false
  },
  "frame": {
    "_class": "rect",
    "constrainProportions": false,
    "do_objectID": "4BA18934-B7C9-43DE-AF96-86A9187DE094",
    "height": 9.604919292851655,
    "width": 39.54761904761904,
    "x": 115.047619047619,
    "y": 32.41660261337432
  },
  "hasClickThrough": false,
  "hasClippingMask": false,
  "isFixedToViewport": false,
  "isFlippedHorizontal": false,
  "isFlippedVertical": false,
  "isLocked": false,
  "isVisible": true,
  "layerListExpandedType": 0,
  "layers": [
    {
      "class": "shapePath",
      "id": "A80FC647-FBD6-436B-BA0B-17FF414B0E2D"
    }
  ],
  "name": "Built-in stereo speaker/microphone",
  "nameIsFixed": true,
  "resizingConstraint": 63,
  "resizingType": 0,
  "rotation": 0,
  "shouldBreakMaskChain": false,
  "style": {
    "_class": "style",
    "blur": {
      "_class": "blur",
      "center": "{0.5, 0.5}",
      "do_objectID": "AA6D751C-AD89-495B-9DBF-25405C323131",
      "isEnabled": false,
      "motionAngle": 0,
      "radius": 6,
      "saturation": 1,
      "type": 0
    },
    "do_objectID": "CA95E1A9-90D3-4BF9-9BE8-D7FCBE01180B",
    "endMarkerType": 0,
    "miterLimit": 10,
    "startMarkerType": 0,
    "windingRule": 1
  }
}