{
  "_class": "group",
  "booleanOperation": 0,
  "clippingMaskMode": 0,
  "do_objectID": "12B1C7A1-1D7C-4711-A71C-9DB3FD9E6EAF",
  "exportOptions": {
    "_class": "exportOptions",
    "do_objectID": "D357BBE0-3ED8-49C5-BE7E-A039534C3FF0",
    "exportFormats": [
    ],
    "includedLayerIds": [
    ],
    "layerOptions": 0,
    "shouldTrim": false
  },
  "frame": {
    "_class": "rect",
    "constrainProportions": false,
    "do_objectID": "0B30BA68-D2ED-4D11-8A4C-DEB98940808A",
    "height": 732,
    "width": 261,
    "x": 7.19047619047619,
    "y": 16.80860876249039
  },
  "hasClickThrough": false,
  "hasClippingMask": false,
  "isFixedToViewport": false,
  "isFlippedHorizontal": false,
  "isFlippedVertical": false,
  "isLocked": false,
  "isVisible": true,
  "layerListExpandedType": 2,
  "layers": [
    {
      "class": "shapePath",
      "id": "70BA8A5A-8DB6-4645-B567-DCD403788BCA"
    },
    {
      "class": "shapePath",
      "id": "20EC5F37-5D62-4E83-8F89-EA59FF087F6F"
    }
  ],
  "name": "Screen",
  "nameIsFixed": true,
  "resizingConstraint": 63,
  "resizingType": 0,
  "rotation": 0,
  "shouldBreakMaskChain": false,
  "style": {
    "_class": "style",
    "blur": {
      "_class": "blur",
      "center": "{0.5, 0.5}",
      "do_objectID": "42CEC0C4-2B72-4ECF-9EA3-2F2450856E34",
      "isEnabled": false,
      "motionAngle": 0,
      "radius": 6,
      "saturation": 1,
      "type": 0
    },
    "do_objectID": "1A8F172D-A91A-45B7-84B2-5B9F3EDBC92B",
    "endMarkerType": 0,
    "miterLimit": 10,
    "startMarkerType": 0,
    "windingRule": 1
  }
}