{
  "_class": "shapePath",
  "booleanOperation": -1,
  "clippingMaskMode": 0,
  "do_objectID": "8E5F7DBA-A1CC-4C42-9270-38B9EC9D66EF",
  "edited": true,
  "exportOptions": {
    "_class": "exportOptions",
    "exportFormats": [
    ],
    "includedLayerIds": [
    ],
    "layerOptions": 0,
    "shouldTrim": false
  },
  "frame": {
    "_class": "rect",
    "constrainProportions": false,
    "height": 0.9982905788876284,
    "width": 6.1907809307605,
    "x": 2.938474460839954,
    "y": 3.497028376844494
  },
  "hasClippingMask": false,
  "isClosed": true,
  "isFixedToViewport": false,
  "isFlippedHorizontal": false,
  "isFlippedVertical": false,
  "isLocked": false,
  "isVisible": true,
  "layerListExpandedType": 0,
  "name": "Path",
  "nameIsFixed": false,
  "pointRadiusBehaviour": 1,
  "points": [
    {
      "_class": "curvePoint",
      "cornerRadius": 0,
      "curveFrom": "{0.079098612084388967, 1}",
      "curveMode": 4,
      "curveTo": "{0.035464105940545707, 1}",
      "hasCurveFrom": false,
      "hasCurveTo": true,
      "point": "{0.079098612084388967, 1}"
    },
    {
      "_class": "curvePoint",
      "cornerRadius": 0,
      "curveFrom": "{0.96453332717280538, 1}",
      "curveMode": 4,
      "curveTo": "{0.92084748329598509, 1}",
      "hasCurveFrom": true,
      "hasCurveTo": false,
      "point": "{0.92084748329598509, 1}"
    },
    {
      "_class": "curvePoint",
      "cornerRadius": 0,
      "curveFrom": "{1, 0.22428805654160275}",
      "curveMode": 2,
      "curveTo": "{1, 0.77601439009248463}",
      "hasCurveFrom": true,
      "hasCurveTo": true,
      "point": "{1, 0.50015122331704376}"
    },
    {
      "_class": "curvePoint",
      "cornerRadius": 0,
      "curveFrom": "{0.92084748329598509, 0}",
      "curveMode": 4,
      "curveTo": "{0.96453332717280538, 0}",
      "hasCurveFrom": false,
      "hasCurveTo": true,
      "point": "{0.92084748329598509, 0}"
    },
    {
      "_class": "curvePoint",
      "cornerRadius": 0,
      "curveFrom": "{0.035464105940545707, 0}",
      "curveMode": 4,
      "curveTo": "{0.079098612084388967, 0}",
      "hasCurveFrom": true,
      "hasCurveTo": false,
      "point": "{0.079098612084388967, 0}"
    },
    {
      "_class": "curvePoint",
      "cornerRadius": 0,
      "curveFrom": "{0, 0.77601439009248563}",
      "curveMode": 2,
      "curveTo": "{0, 0.22428805654160183}",
      "hasCurveFrom": true,
      "hasCurveTo": true,
      "point": "{0, 0.50015122331704376}"
    }
  ],
  "resizingConstraint": 63,
  "resizingType": 0,
  "rotation": 0,
  "shouldBreakMaskChain": false,
  "style": {
    "_class": "style",
    "blur": {
      "_class": "blur",
      "center": "{0.5, 0.5}",
      "isEnabled": false,
      "motionAngle": 0,
      "radius": 1.953125,
      "saturation": 1,
      "type": 0
    },
    "endMarkerType": 0,
    "miterLimit": 10,
    "startMarkerType": 0,
    "windingRule": 1
  }
}